[
  {
    "title": "Lee Robinson",
    "description": "VP of Product at Vercel. A masterclass in minimalist design and technical writing.",
    "url": "https://leerob.io",
    "githubUrl": "https://github.com/leerob",
    "category": "Portfolio",
    "tags": ["#Nextjs", "#Tailwind", "#Writing"],
    "featured": true,
    "dateAdded": "2026-05-12",
    "image": "https://api.microlink.io/?url=https://leerob.io&screenshot=true&embed=screenshot.url"
  },
  {
    "title": "Brittany Chiang",
    "description": "Software Engineer at Upstatement. Famous for the most-forked dark-themed portfolio.",
    "url": "https://brittanychiang.com",
    "githubUrl": "https://github.com/bchiang7",
    "category": "Portfolio",
    "tags": ["#Gatsby", "#React", "#SCSS"],
    "featured": true,
    "dateAdded": "2026-05-12",
    "image": "https://api.microlink.io/?url=https://brittanychiang.com&screenshot=true&embed=screenshot.url"
  },
  {
    "title": "Josh W. Comeau",
    "description": "An interactive portfolio with custom animations and brilliant educational UI.",
    "url": "https://joshwcomeau.com",
    "githubUrl": "https://github.com/joshwcomeau",
    "category": "Portfolio",
    "tags": ["#React", "#Animation", "#Nextjs"],
    "featured": true,
    "dateAdded": "2026-05-12",
    "image": "https://api.microlink.io/?url=https://joshwcomeau.com&screenshot=true&embed=screenshot.url"
  },
  {
    "title": "Rauno Freiberg",
    "description": "Design Engineer at Vercel. Focuses on high-end micro-interactions and sleek aesthetics.",
    "url": "https://rauno.me",
    "githubUrl": "https://github.com/rauno6",
    "category": "Portfolio",
    "tags": ["#Nextjs", "#FramerMotion", "#UI"],
    "featured": true,
    "dateAdded": "2026-05-12",
    "image": "https://api.microlink.io/?url=https://rauno.me&screenshot=true&embed=screenshot.url"
  },
  {
    "title": "Manu Arora",
    "description": "Founder of Aceternity UI. Showcases complex animations and modern component libraries.",
    "url": "https://manuarora.in",
    "githubUrl": "https://github.com/manuarora700",
    "category": "Portfolio",
    "tags": ["#Nextjs", "#Tailwind", "#Animation"],
    "featured": false,
    "dateAdded": "2026-05-12",
    "image": "https://api.microlink.io/?url=https://manuarora.in&screenshot=true&embed=screenshot.url"
  },
  {
    "title": "Delba de Oliveira",
    "description": "Developer Advocate at Vercel. Explores interactive technical layouts and Next.js features.",
    "url": "https://delba.dev",
    "githubUrl": "https://github.com/delbaoliveira",
    "category": "Portfolio",
    "tags": ["#Nextjs", "#TypeScript", "#React"],
    "featured": false,
    "dateAdded": "2026-05-12",
    "image": "https://api.microlink.io/?url=https://delba.dev&screenshot=true&embed=screenshot.url"
  },
  {
    "title": "Ahmad Sandid",
    "description": "Full-stack engineer specializing in high-performance 3D web experiences.",
    "url": "https://ahmadsandid.com",
    "githubUrl": "https://github.com/ahmadsandid",
    "category": "Portfolio",
    "tags": ["#ThreeJS", "#3D", "#Nextjs"],
    "featured": true,
    "dateAdded": "2026-05-12",
    "image": "https://api.microlink.io/?url=https://ahmadsandid.com&screenshot=true&embed=screenshot.url"
  },
  {
    "title": "Paco Coursey",
    "description": "Creator of next-themes. Known for hyper-minimalist and lightning-fast interfaces.",
    "url": "https://paco.me",
    "githubUrl": "https://github.com/pacocoursey",
    "category": "Portfolio",
    "tags": ["#Nextjs", "#Minimalist", "#UX"],
    "featured": false,
    "dateAdded": "2026-05-12",
    "image": "https://api.microlink.io/?url=https://paco.me&screenshot=true&embed=screenshot.url"
  },
  {
    "title": "Hamed Bahram",
    "description": "Expert Next.js developer focusing on clean architecture and modern web patterns.",
    "url": "https://hamedbahram.io",
    "githubUrl": "https://github.com/hamedbahram",
    "category": "Portfolio",
    "tags": ["#Nextjs", "#Fullstack", "#React"],
    "featured": false,
    "dateAdded": "2026-05-12",
    "image": "https://api.microlink.io/?url=https://hamedbahram.io&screenshot=true&embed=screenshot.url"
  },
  {
    "title": "T3 Dot GG (Theo)",
    "description": "Focuses on the T3 Stack, bleeding-edge performance, and simplified development workflows.",
    "url": "https://t3.gg",
    "githubUrl": "https://github.com/t3-oss",
    "category": "Portfolio",
    "tags": ["#T3Stack", "#Nextjs", "#TypeScript"],
    "featured": false,
    "dateAdded": "2026-05-12",
    "image": "https://api.microlink.io/?url=https://t3.gg&screenshot=true&embed=screenshot.url"
  },
  {
    "title": "Emil Kowalski",
    "description": "Design Engineer at Vercel. Known for creating 'Sonner' and mastering micro-interactions.",
    "url": "https://emilkowal.ski",
    "githubUrl": "https://github.com/emilkowalski",
    "category": "Portfolio",
    "tags": ["#DesignEngineer", "#Animations", "#Nextjs"],
    "featured": true,
    "dateAdded": "2026-05-12",
    "image": "https://api.microlink.io/?url=https://emilkowal.ski&screenshot=true&embed=screenshot.url"
  },
  {
    "title": "Steph Ango",
    "description": "CEO of Obsidian. Focuses on typography, minimalist aesthetics, and personal tools.",
    "url": "https://stephango.com",
    "githubUrl": "https://github.com/kepano",
    "category": "Portfolio",
    "tags": ["#Minimalist", "#Typography", "#Product"],
    "featured": false,
    "dateAdded": "2026-05-12",
    "image": "https://api.microlink.io/?url=https://stephango.com&screenshot=true&embed=screenshot.url"
  },
  {
    "title": "Dan Abramov",
    "description": "Co-author of Redux and Create React App. Deep insights into React internals.",
    "url": "https://overreacted.io",
    "githubUrl": "https://github.com/gaearon",
    "category": "Blog",
    "tags": ["#React", "#JavaScript", "#PersonalBlog"],
    "featured": false,
    "dateAdded": "2026-05-12",
    "image": "https://api.microlink.io/?url=https://overreacted.io&screenshot=true&embed=screenshot.url"
  },
  {
    "title": "Monica Powell",
    "description": "Software Engineer and GitHub Star. Focuses on community and web development.",
    "url": "https://www.monicapowell.com",
    "githubUrl": "https://github.com/m0nica",
    "category": "Portfolio",
    "tags": ["#WebDev", "#GitHubStar", "#React"],
    "featured": false,
    "dateAdded": "2026-05-12",
    "image": "https://api.microlink.io/?url=https://www.monicapowell.com&screenshot=true&embed=screenshot.url"
  },
  {
    "title": "Bastien Falcou",
    "description": "A visually stunning interactive portfolio with high-end animations.",
    "url": "https://bastienfalcou.com",
    "githubUrl": "https://github.com/bastienfalcou",
    "category": "Portfolio",
    "tags": ["#Creative", "#Animation", "#Swift"],
    "featured": true,
    "dateAdded": "2026-05-12",
    "image": "https://api.microlink.io/?url=https://bastienfalcou.com&screenshot=true&embed=screenshot.url"
  },
  {
    "title": "Kent C. Dodds",
    "description": "Creator of Epic React and Remix expert. High-performance educational site.",
    "url": "https://kentcdodds.com",
    "githubUrl": "https://github.com/kentcdodds",
    "category": "Portfolio",
    "tags": ["#Remix", "#Testing", "#React"],
    "featured": false,
    "dateAdded": "2026-05-12",
    "image": "https://api.microlink.io/?url=https://kentcdodds.com&screenshot=true&embed=screenshot.url"
  },
  {
    "title": "Robin Wieruch",
    "description": "Full-stack developer and author. Minimalist focus on React and Node.js.",
    "url": "https://www.robinwieruch.de",
    "githubUrl": "https://github.com/rwieruch",
    "category": "Blog",
    "tags": ["#React", "#Nodejs", "#Minimalist"],
    "featured": false,
    "dateAdded": "2026-05-12",
    "image": "https://api.microlink.io/?url=https://www.robinwieruch.de&screenshot=true&embed=screenshot.url"
  },
  {
    "title": "Nuno Maduro",
    "description": "Creator of PEST PHP and Laravel Core Team Member. Sleek developer site.",
    "url": "https://nunomaduro.com",
    "githubUrl": "https://github.com/nunomaduro",
    "category": "Portfolio",
    "tags": ["#PHP", "#Laravel", "#OpenSource"],
    "featured": false,
    "dateAdded": "2026-05-12",
    "image": "https://api.microlink.io/?url=https://nunomaduro.com&screenshot=true&embed=screenshot.url"
  },
  {
    "title": "Yuan Chuan",
    "description": "CSS artist. Portfolio showcases mind-blowing generative art using CSS.",
    "url": "https://yuanchuan.dev",
    "githubUrl": "https://github.com/yuanchuan",
    "category": "Creative",
    "tags": ["#CSS", "#GenerativeArt", "#SVG"],
    "featured": true,
    "dateAdded": "2026-05-12",
    "image": "https://api.microlink.io/?url=https://yuanchuan.dev&screenshot=true&embed=screenshot.url"
  },
  {
    "title": "Tanner Linsley",
    "description": "Creator of TanStack (React Query). High-performance engineering portfolio.",
    "url": "https://tannerlinsley.com",
    "githubUrl": "https://github.com/tannerlinsley",
    "category": "Portfolio",
    "tags": ["#TanStack", "#React", "#OpenSource"],
    "featured": false,
    "dateAdded": "2026-05-12",
    "image": "https://api.microlink.io/?url=https://tannerlinsley.com&screenshot=true&embed=screenshot.url"
  },
  {
    "title": "Sara Soueidan",
    "description": "Independent UI engineer and accessibility expert. Very clean and accessible site.",
    "url": "https://www.sarasoueidan.com",
    "githubUrl": "https://github.com/sarasoueidan",
    "category": "Portfolio",
    "tags": ["#Accessibility", "#SVG", "#UI"],
    "featured": false,
    "dateAdded": "2026-05-12",
    "image": "https://api.microlink.io/?url=https://www.sarasoueidan.com&screenshot=true&embed=screenshot.url"
  },
  {
    "title": "Bruno Simon",
    "description": "Famous for his 3D car-game portfolio. Built with Three.js.",
    "url": "https://bruno-simon.com",
    "githubUrl": "https://github.com/brunosimon",
    "category": "Portfolio",
    "tags": ["#ThreeJS", "#3D", "#WebGL"],
    "featured": true,
    "dateAdded": "2026-05-12",
    "image": "https://api.microlink.io/?url=https://bruno-simon.com&screenshot=true&embed=screenshot.url"
  },
  {
    "title": "Coby Chapple",
    "description": "Product Designer at GitHub. Great example of case-study focused portfolio.",
    "url": "https://cobychapple.com",
    "githubUrl": "",
    "category": "Design",
    "tags": ["#ProductDesign", "#GitHub", "#UX"],
    "featured": false,
    "dateAdded": "2026-05-12",
    "image": "https://api.microlink.io/?url=https://cobychapple.com&screenshot=true&embed=screenshot.url"
  },
  {
    "title": "Andy Bell",
    "description": "Founder of Set Studio. Focus on modern CSS and progressive enhancement.",
    "url": "https://andy-bell.me",
    "githubUrl": "https://github.com/andybelldesign",
    "category": "Portfolio",
    "tags": ["#CSS", "#WebDesign", "#Performance"],
    "featured": false,
    "dateAdded": "2026-05-12",
    "image": "https://api.microlink.io/?url=https://andy-bell.me&screenshot=true&embed=screenshot.url"
  },
  {
    "title": "Jack Forge",
    "description": "Software Engineer and Twitter personality. Very distinct and colorful UI.",
    "url": "https://jackforge.com",
    "githubUrl": "https://github.com/jackforge",
    "category": "Portfolio",
    "tags": ["#React", "#SaaS", "#UI"],
    "featured": false,
    "dateAdded": "2026-05-12",
    "image": "https://api.microlink.io/?url=https://jackforge.com&screenshot=true&embed=screenshot.url"
  },
  {
    "title": "Lynn Fisher",
    "description": "Famous for her single-div CSS illustrations and annual site redesigns.",
    "url": "https://lynnandtonic.com",
    "githubUrl": "https://github.com/lynnandtonic",
    "category": "Creative",
    "tags": ["#CSS", "#Illustration", "#Design"],
    "featured": true,
    "dateAdded": "2026-05-12",
    "image": "https://api.microlink.io/?url=https://lynnandtonic.com&screenshot=true&embed=screenshot.url"
  },
  {
    "title": "Ryan Florence",
    "description": "Co-creator of React Router and Remix. Clean and fast developer site.",
    "url": "https://ryanflorence.com",
    "githubUrl": "https://github.com/ryanflorence",
    "category": "Portfolio",
    "tags": ["#React", "#Remix", "#JavaScript"],
    "featured": false,
    "dateAdded": "2026-05-12",
    "image": "https://api.microlink.io/?url=https://ryanflorence.com&screenshot=true&embed=screenshot.url"
  },
  {
    "title": "Sarah Drasner",
    "description": "Engineering Leader at Google. Focuses on SVG animations and developer experience.",
    "url": "https://sarah.dev",
    "githubUrl": "https://github.com/sdras",
    "category": "Portfolio",
    "tags": ["#SVG", "#Vue", "#Engineering"],
    "featured": false,
    "dateAdded": "2026-05-12",
    "image": "https://api.microlink.io/?url=https://sarah.dev&screenshot=true&embed=screenshot.url"
  }
]
